recommender_agent/__init__.py
recommender_agent/recommenderSystem.py
recommender_agent/components/__init__.py
recommender_agent/components/agent.py
recommender_agent/components/vectorStoreClient.py
recommender_agent-0.3.1.dist-info/LICENSE
recommender_agent-0.3.1.dist-info/METADATA
recommender_agent-0.3.1.dist-info/WHEEL
recommender_agent-0.3.1.dist-info/top_level.txt
recommender_agent-0.3.1.dist-info/RECORD
