Metadata-Version: 2.1
Name: recommender-agent
Version: 0.3.1
Summary: En el presente proyecto muestro la construcción de una sistema de recomendación, el sistema permite recomendar recursos a través del uso de mecanismos de Procesamiento de lenguaje natura como agentes langchain, IA generatica y embeddings.
Home-page: https://github.com/johansquintero/recommender-agent
Author: Johan sebastian quintero rojas
Author-email: metalium144@gmail.com
License: MIT
License-File: LICENSE
Requires-Dist: numpy ==1.25.2
Requires-Dist: pandas ==2.0.3
Requires-Dist: typer ==0.9.4
Requires-Dist: scipy ==1.11.4
Requires-Dist: langchain ==0.1.17
Requires-Dist: langchain-community ==0.0.36
Requires-Dist: chromadb ==0.5.0
Requires-Dist: openai ==1.25.1
Requires-Dist: langchain-openai ==0.1.6
Requires-Dist: groq ==0.5.0
Requires-Dist: langchain-groq ==0.1.3
Requires-Dist: sentence-transformers ==2.7.0
Requires-Dist: torch ==2.2.1
